README.md
setup.cfg
setup.py
fintechlab/CommonFunction.py
fintechlab/__init__.py
fintechlab.egg-info/PKG-INFO
fintechlab.egg-info/SOURCES.txt
fintechlab.egg-info/dependency_links.txt
fintechlab.egg-info/requires.txt
fintechlab.egg-info/top_level.txt