Metadata-Version: 1.0
Name: fintechlab
Version: 0.1.3
Summary: Fintech API
Home-page: https://github.com/hyokwan
Author: kimhyokwan
Author-email: haiteam@naver.com
License: MIT
Platform: UNKNOWN
